<object statesCount="2" startState="0" radius="15" offsetX="-4" offsetY="0" container="false">
    <state id="0"
           switchable="true"
           switchCondition=""
           tex="rod"
           texType="sprite"
           fps="0"
           looping="false"
           framesCount="1"
           
           flagName=""
           flagVal="false"
           
           emitsParticle="-1"
           emitX="0"
           emitY="0"
           emitZ="0"
           emitInterval="0"
           
           switchSound=""
           loopSound=""
           loopVolume="0"
           
           hidePlayer="false"/> 
    <state id="1"
           switchable="true"
           switchCondition=""
           tex="rod_use"
           texType="anim"
           fps="10"
           looping="true"
           framesCount="8"
           
           flagName=""
           flagVal="true"
           
           emitsParticle="-1"
           emitX="0"
           emitY="0"
           emitZ="0"
           emitInterval="0"
           
           switchSound=""
           loopSound=""
           loopVolume="0"

           hidePlayer="true"
           drawPlayer="true"/> 
    <frames id="1">
        <frame head="left" headX="8" headY="37" body="left" bodyX="5" bodyY="20"/>
        <frame head="left" headX="12" headY="41" body="left" bodyX="9" bodyY="24"/>
        <frame head="left" headX="13" headY="48" body="left" bodyX="10" bodyY="31"/>
        <frame head="left" headX="12" headY="50" body="left" bodyX="10" bodyY="35"/>
        <frame head="left" headX="12" headY="44" body="left" bodyX="9" bodyY="25"/>
        <frame head="left" headX="8" headY="37" body="left" bodyX="5" bodyY="20"/>
        <frame head="left" headX="8" headY="37" body="left" bodyX="5" bodyY="20"/>
        <frame head="left" headX="8" headY="37" body="left" bodyX="5" bodyY="20"/>
    </frames>
</object>